fishy/__init__.py
fishy/__main__.py
fishy/beep.wav
fishy/constants.py
fishy/fishybot_logo.png
fishy/icon.ico
fishy/sound.mp3
fishy/version.txt
fishy/engine/__init__.py
fishy/engine/common/IEngine.py
fishy/engine/common/__init__.py
fishy/engine/common/event_handler.py
fishy/engine/common/qr_detection.py
fishy/engine/common/screenshot.py
fishy/engine/common/window.py
fishy/engine/common/window_server.py
fishy/engine/fullautofisher/__init__.py
fishy/engine/fullautofisher/controls.py
fishy/engine/fullautofisher/engine.py
fishy/engine/fullautofisher/test.py
fishy/engine/fullautofisher/mode/__init__.py
fishy/engine/fullautofisher/mode/calibrator.py
fishy/engine/fullautofisher/mode/imode.py
fishy/engine/fullautofisher/mode/player.py
fishy/engine/fullautofisher/mode/recorder.py
fishy/engine/semifisher/__init__.py
fishy/engine/semifisher/engine.py
fishy/engine/semifisher/fishing_event.py
fishy/engine/semifisher/fishing_mode.py
fishy/gui/__init__.py
fishy/gui/config_top.py
fishy/gui/discord_login.py
fishy/gui/funcs.py
fishy/gui/gui.py
fishy/gui/log_config.py
fishy/gui/main_gui.py
fishy/gui/splash.py
fishy/gui/terms_gui.py
fishy/gui/update_dialog.py
fishy/helper/__init__.py
fishy/helper/active_poll.py
fishy/helper/auto_update.py
fishy/helper/config.py
fishy/helper/depless.py
fishy/helper/helper.py
fishy/helper/luaparser.py
fishy/helper/migration.py
fishy/helper/popup.py
fishy/helper/hotkey/__init__.py
fishy/helper/hotkey/hotkey_process.py
fishy/helper/hotkey/process.py
fishy/libs/__init__.py
fishy/libs/tkhtmlview/__init__.py
fishy/libs/tkhtmlview/html_parser.py
fishy/osservices/__init__.py
fishy/osservices/linux.py
fishy/osservices/os_services.py
fishy/osservices/windows.py
fishy/web/__init__.py
fishy/web/decorators.py
fishy/web/urls.py
fishy/web/web.py
fishy-0.5.26.dist-info/LICENSE
fishy-0.5.26.dist-info/METADATA
fishy-0.5.26.dist-info/WHEEL
fishy-0.5.26.dist-info/entry_points.txt
fishy-0.5.26.dist-info/top_level.txt
fishy-0.5.26.dist-info/RECORD
