Metadata-Version: 2.1
Name: fishy
Version: 0.5.26
Summary: Fishing bot for Elder Scrolls Online
Home-page: https://github.com/adsau59/fishyboteso
Author: Adam Saudagar
Author-email: adam_saudagar@live.com
License: MIT
Project-URL: Bug Reports, https://github.com/adsau59/fishyboteso/issues/
Project-URL: Funding, https://www.paypal.me/AdamSaudagar
Project-URL: Say Thanks!, http://discord.definex.in
Project-URL: Source, https://github.com/adsau59/fishyboteso
Keywords: fishybot fishyboteso esofishingbot fishingbot esobot
Classifier: Development Status :: 3 - Alpha
Classifier: Intended Audience :: End Users/Desktop
Classifier: License :: OSI Approved :: MIT License
Classifier: Programming Language :: Python :: 3.7
Classifier: Programming Language :: Python :: 3.8
Requires-Python: >=3.7
License-File: LICENSE
Requires-Dist: urllib3
Requires-Dist: imutils
Requires-Dist: numpy
Requires-Dist: opencv-python
Requires-Dist: Pillow
Requires-Dist: ttkthemes
Requires-Dist: requests
Requires-Dist: whatsmyip
Requires-Dist: pynput
Requires-Dist: keyboard
Requires-Dist: playsound ==1.2.2
Requires-Dist: event-scheduler
Requires-Dist: mouse
Requires-Dist: pyautogui
Requires-Dist: mss
Requires-Dist: pypiwin32 ; platform_system == "Windows"
Requires-Dist: winshell ; platform_system == "Windows"
